instapy/__init__.py
instapy/__main__.py
instapy/cli.py
instapy/io.py
instapy/numba_filters.py
instapy/numpy_filters.py
instapy/profiling.py
instapy/python_filters.py
instapy/timing.py
knutthol_instapy-0.1.0.dist-info/METADATA
knutthol_instapy-0.1.0.dist-info/WHEEL
knutthol_instapy-0.1.0.dist-info/top_level.txt
knutthol_instapy-0.1.0.dist-info/RECORD
