Metadata-Version: 2.1
Name: knutthol-instapy
Version: 0.1.0
Summary: in3110 assignment3
License: MIT License
Requires-Python: >=3.7
